dc_cli/__init__.py
dc_cli/dc.py
dc_cli_jawide-0.0.2.dist-info/METADATA
dc_cli_jawide-0.0.2.dist-info/WHEEL
dc_cli_jawide-0.0.2.dist-info/entry_points.txt
dc_cli_jawide-0.0.2.dist-info/licenses/LICENSE
dc_cli_jawide-0.0.2.dist-info/RECORD
