Metadata-Version: 2.1
Name: dc-cli-jawide
Version: 0.0.2
Summary: DC software cli
Project-URL: Homepage, https://github.com/jawide/dc-cli
Project-URL: Bug Tracker, https://github.com/jawide/dc-cli/issues
Author-email: Jawide <jawide@qq.com>
License: MIT License
Classifier: License :: OSI Approved :: MIT License
Classifier: Operating System :: OS Independent
Classifier: Programming Language :: Python :: 3
Requires-Python: >=3.7
